LICENSE
README.rst
setup.cfg
setup.py
restructuredBootstrap/__init__.py
restructuredBootstrap/alert.py
restructuredBootstrap/buttons.py
restructuredBootstrap/callout.py
restructuredBootstrap/clearfix.py
restructuredBootstrap/container.py
restructuredBootstrap/custom_pygments_style.py
restructuredBootstrap/grid.py
restructuredBootstrap/hr.py
restructuredBootstrap/html_translator.py
restructuredBootstrap/list_group.py
restructuredBootstrap/media.py
restructuredBootstrap/modal.py
restructuredBootstrap/panel.py
restructuredBootstrap/paragraph.py
restructuredBootstrap/progress_bar.py
restructuredBootstrap/tabs.py
restructuredBootstrap.egg-info/PKG-INFO
restructuredBootstrap.egg-info/SOURCES.txt
restructuredBootstrap.egg-info/dependency_links.txt
restructuredBootstrap.egg-info/not-zip-safe
restructuredBootstrap.egg-info/requires.txt
restructuredBootstrap.egg-info/top_level.txt
restructuredBootstrap/roles/__init__.py
restructuredBootstrap/roles/fontawesome.py
restructuredBootstrap/roles/inline_abbr.py
restructuredBootstrap/roles/inline_background_contextual.py
restructuredBootstrap/roles/inline_badge.py
restructuredBootstrap/roles/inline_heading.py
restructuredBootstrap/roles/inline_label.py
restructuredBootstrap/roles/inline_text.py
restructuredBootstrap/roles/inline_text_alignment.py
restructuredBootstrap/roles/inline_text_contextual.py
restructuredBootstrap/roles/inline_text_transform.py
restructuredBootstrap/roles/inline_tooltip.py