Metadata-Version: 1.1
Name: restructuredBootstrap
Version: 1.0.0
Summary: Twitter Bootstrap 3 directives for use with Sphinx.
Home-page: https://github.com/lakhman/restructuredBootstrap
Author: Anil Lakhman
Author-email: restructured.bootstrap@anil.io
License: The MIT License
